frequenz/core/__init__.py
frequenz/core/conftest.py
frequenz/core/datetime.py
frequenz/core/enum.py
frequenz/core/id.py
frequenz/core/math.py
frequenz/core/module.py
frequenz/core/py.typed
frequenz/core/typing.py
frequenz_core-1.3.0.dist-info/licenses/LICENSE
frequenz_core-1.3.0.dist-info/METADATA
frequenz_core-1.3.0.dist-info/WHEEL
frequenz_core-1.3.0.dist-info/top_level.txt
frequenz_core-1.3.0.dist-info/RECORD
