Metadata-Version: 2.4
Name: frequenz-core
Version: 1.3.0
Summary: Core utilities to complement Python's standard library
Author-email: Frequenz Energy-as-a-Service GmbH <floss@frequenz.com>
License: MIT
Project-URL: Documentation, https://frequenz-floss.github.io/frequenz-core-python/
Project-URL: Changelog, https://github.com/frequenz-floss/frequenz-core-python/releases
Project-URL: Issues, https://github.com/frequenz-floss/frequenz-core-python/issues
Project-URL: Repository, https://github.com/frequenz-floss/frequenz-core-python
Project-URL: Support, https://github.com/frequenz-floss/frequenz-core-python/discussions/categories/support
Keywords: asyncio,collections,core,datetime,frequenz,lib,library,math,python,stdlib,typing
Classifier: Development Status :: 5 - Production/Stable
Classifier: Intended Audience :: Developers
Classifier: License :: OSI Approved :: MIT License
Classifier: Programming Language :: Python :: 3
Classifier: Programming Language :: Python :: 3 :: Only
Classifier: Topic :: Software Development :: Libraries
Classifier: Typing :: Typed
Requires-Python: <4,>=3.11
License-File: LICENSE
Requires-Dist: typing-extensions<5,>=4.13.0
Provides-Extra: dev-flake8
Requires-Dist: flake8==7.3.0; extra == "dev-flake8"
Requires-Dist: flake8-docstrings==1.7.0; extra == "dev-flake8"
Requires-Dist: flake8-pyproject==1.2.3; extra == "dev-flake8"
Requires-Dist: pydoclint==0.6.11; extra == "dev-flake8"
Requires-Dist: pydocstyle==6.3.0; extra == "dev-flake8"
Provides-Extra: dev-formatting
Requires-Dist: black==25.1.0; extra == "dev-formatting"
Requires-Dist: isort==6.0.1; extra == "dev-formatting"
Provides-Extra: dev-mkdocs
Requires-Dist: Markdown==3.8.2; extra == "dev-mkdocs"
Requires-Dist: black==25.1.0; extra == "dev-mkdocs"
Requires-Dist: mike==2.1.3; extra == "dev-mkdocs"
Requires-Dist: mkdocs-gen-files==0.5.0; extra == "dev-mkdocs"
Requires-Dist: mkdocs-literate-nav==0.6.2; extra == "dev-mkdocs"
Requires-Dist: mkdocs-macros-plugin==1.3.9; extra == "dev-mkdocs"
Requires-Dist: mkdocs-material==9.6.18; extra == "dev-mkdocs"
Requires-Dist: mkdocstrings[python]==0.30.0; extra == "dev-mkdocs"
Requires-Dist: mkdocstrings-python==1.18.2; extra == "dev-mkdocs"
Requires-Dist: frequenz-repo-config[lib]==0.13.5; extra == "dev-mkdocs"
Provides-Extra: dev-mypy
Requires-Dist: mypy==1.17.1; extra == "dev-mypy"
Requires-Dist: types-Markdown==3.8.0.20250809; extra == "dev-mypy"
Requires-Dist: frequenz-core[dev-mkdocs,dev-noxfile,dev-pytest]; extra == "dev-mypy"
Provides-Extra: dev-noxfile
Requires-Dist: nox==2025.5.1; extra == "dev-noxfile"
Requires-Dist: frequenz-repo-config[lib]==0.13.5; extra == "dev-noxfile"
Provides-Extra: dev-pylint
Requires-Dist: frequenz-core[dev-mkdocs,dev-noxfile,dev-pytest]; extra == "dev-pylint"
Provides-Extra: dev-pytest
Requires-Dist: pytest==8.4.1; extra == "dev-pytest"
Requires-Dist: pylint==3.3.8; extra == "dev-pytest"
Requires-Dist: frequenz-repo-config[extra-lint-examples]==0.13.5; extra == "dev-pytest"
Requires-Dist: pytest-mock==3.14.1; extra == "dev-pytest"
Requires-Dist: pytest-asyncio==1.1.0; extra == "dev-pytest"
Requires-Dist: async-solipsism==0.8; extra == "dev-pytest"
Requires-Dist: hypothesis==6.138.11; extra == "dev-pytest"
Provides-Extra: dev
Requires-Dist: frequenz-core[dev-flake8,dev-formatting,dev-mkdocs,dev-mypy,dev-noxfile,dev-pylint,dev-pytest]; extra == "dev"
Dynamic: license-file
